odoo/addons/account_voucher_killer/README.rst
odoo/addons/account_voucher_killer/__init__.py
odoo/addons/account_voucher_killer/__manifest__.py
odoo/addons/account_voucher_killer/i18n/account_voucher_killer.pot
odoo/addons/account_voucher_killer/i18n/ca_ES.po
odoo/addons/account_voucher_killer/i18n/es.po
odoo/addons/account_voucher_killer/i18n/fr.po
odoo/addons/account_voucher_killer/i18n/it.po
odoo/addons/account_voucher_killer/i18n/pt_BR.po
odoo/addons/account_voucher_killer/i18n/sl.po
odoo/addons/account_voucher_killer/readme/CONFIGURE.md
odoo/addons/account_voucher_killer/readme/CONTRIBUTORS.md
odoo/addons/account_voucher_killer/readme/DESCRIPTION.md
odoo/addons/account_voucher_killer/security/invoice_data.xml
odoo/addons/account_voucher_killer/static/description/icon.png
odoo/addons/account_voucher_killer/static/description/index.html
odoo/addons/account_voucher_killer/view/invoice_view.xml
odoo_addon_account_voucher_killer-18.0.1.0.0.4.dist-info/METADATA
odoo_addon_account_voucher_killer-18.0.1.0.0.4.dist-info/WHEEL
odoo_addon_account_voucher_killer-18.0.1.0.0.4.dist-info/top_level.txt
odoo_addon_account_voucher_killer-18.0.1.0.0.4.dist-info/RECORD
